maida/__init__.py
maida/merge_ts_2_mp4.py
maida/mail/__init__.py
maida/ocr/__init__.py
maida-0.2.1.dist-info/LICENSE
maida-0.2.1.dist-info/METADATA
maida-0.2.1.dist-info/WHEEL
maida-0.2.1.dist-info/top_level.txt
maida-0.2.1.dist-info/RECORD
