Metadata-Version: 2.1
Name: maida
Version: 0.2.1
Summary: No description.
Home-page: https://github.com/LZC6244/maida
Author: maida
Author-email: 624486877@qq.com
Classifier: Programming Language :: Python :: 3
Classifier: License :: OSI Approved :: MIT License
Classifier: Operating System :: OS Independent
Requires-Python: >=3.7
License-File: LICENSE
Provides-Extra: ocr
Requires-Dist: cnocr (>=2.2.2.1) ; extra == 'ocr'
